testwizard/commands_video/CaptureReferenceBitmapCommand.py
testwizard/commands_video/ClearOnScreenDisplayCommand.py
testwizard/commands_video/CompareCommand.py
testwizard/commands_video/CompareResult.py
testwizard/commands_video/CountLastPatternMatchesCommand.py
testwizard/commands_video/CountLastPatternMatchesResult.py
testwizard/commands_video/DeleteAllRecordingsCommand.py
testwizard/commands_video/DeleteAllSnapshotsCommand.py
testwizard/commands_video/DetectMotionCommand.py
testwizard/commands_video/DetectMotionResult.py
testwizard/commands_video/DetectNoMotionCommand.py
testwizard/commands_video/FilterBlackWhiteCommand.py
testwizard/commands_video/FilterCBICommand.py
testwizard/commands_video/FilterColorBlackWhiteCommand.py
testwizard/commands_video/FilterGrayscaleCommand.py
testwizard/commands_video/FilterInvertCommand.py
testwizard/commands_video/FilterResult.py
testwizard/commands_video/FindAllPatternLocationsCommand.py
testwizard/commands_video/FindAllPatternLocationsExCommand.py
testwizard/commands_video/FindAllPatternLocationsResult.py
testwizard/commands_video/FindPatternCommand.py
testwizard/commands_video/FindPatternExCommand.py
testwizard/commands_video/FindPatternResult.py
testwizard/commands_video/GetVideoResolutionCommand.py
testwizard/commands_video/GetVideoResolutionResult.py
testwizard/commands_video/LoadReferenceBitmapCommand.py
testwizard/commands_video/SaveFileResult.py
testwizard/commands_video/SaveReferenceBitmapCommand.py
testwizard/commands_video/SaveRegionCommand.py
testwizard/commands_video/SetAttributeOnScreenDisplayCommand.py
testwizard/commands_video/SetRegionCommand.py
testwizard/commands_video/SetTextOnScreenDisplayCommand.py
testwizard/commands_video/SnapShotBMPCommand.py
testwizard/commands_video/SnapShotCommand.py
testwizard/commands_video/SnapShotJPGCommand.py
testwizard/commands_video/StartBackgroundCaptureCommand.py
testwizard/commands_video/StartRecordingCommand.py
testwizard/commands_video/StopBackgroundCaptureCommand.py
testwizard.commands_video-3.8.1.dist-info/LICENSE.txt
testwizard.commands_video-3.8.1.dist-info/METADATA
testwizard.commands_video-3.8.1.dist-info/WHEEL
testwizard.commands_video-3.8.1.dist-info/top_level.txt
testwizard.commands_video-3.8.1.dist-info/RECORD
